scanner.py
pdf_metadata_scanner-0.1.2.dist-info/licenses/LICENSE
pdf_metadata_scanner-0.1.2.dist-info/METADATA
pdf_metadata_scanner-0.1.2.dist-info/WHEEL
pdf_metadata_scanner-0.1.2.dist-info/entry_points.txt
pdf_metadata_scanner-0.1.2.dist-info/top_level.txt
pdf_metadata_scanner-0.1.2.dist-info/RECORD
