Metadata-Version: 2.4
Name: pdf-metadata-scanner
Version: 0.1.2
Summary: A CLI tool for extracting and analyzing metadata from PDFs, including embedded images and XMP/RDF metadata.
Author: Anne Jan Brouwer
License-Expression: MIT
Keywords: PDF,metadata,scanner,EXIF,XMP
Requires-Python: >=3.11
License-File: LICENSE
Requires-Dist: pikepdf
Requires-Dist: pypdf
Requires-Dist: Pillow
Requires-Dist: tqdm
Dynamic: license-file
